mongostat_fdw/utils.py
mongostat_fdw/__init__.py
mongostat_fdw-0.0.1.dist-info/DESCRIPTION.rst
mongostat_fdw-0.0.1.dist-info/top_level.txt
mongostat_fdw-0.0.1.dist-info/WHEEL
mongostat_fdw-0.0.1.dist-info/metadata.json
mongostat_fdw-0.0.1.dist-info/RECORD
mongostat_fdw-0.0.1.dist-info/METADATA
