Metadata-Version: 2.0
Name: mongostat-fdw
Version: 0.0.1
Summary: mongo databases and collections statistics fdw for postgresql
Home-page: https://bitbucket.org/olshevskiy87/mongostat_fdw
Author: Dmitriy Olshevskiy
Author-email: olshevskiy87@bk.ru
License: MIT
Keywords: mongo mongodb stat statistics collection fdw wrapper postgresql
Platform: UNKNOWN
Requires-Dist: pymongo
